simplecalculator24/__init__.py
simplecalculator24/calculations.py
simplecalculator24-0.0.1.dist-info/METADATA
simplecalculator24-0.0.1.dist-info/WHEEL
simplecalculator24-0.0.1.dist-info/top_level.txt
simplecalculator24-0.0.1.dist-info/RECORD
