Metadata-Version: 2.1
Name: simplecalculator24
Version: 0.0.1
Summary: Package to get calculator
Author: Shravani Mpore
Author-email: shramore58@gmail.com
Classifier: Programming Language :: Python :: 3
Classifier: License :: OSI Approved :: MIT License
Classifier: Operating System :: OS Independent
Requires-Python: >=3.7
